setup.py
runpy_tool/__init__.py
runpy_tool/runpy.py
runpy_tool.egg-info/PKG-INFO
runpy_tool.egg-info/SOURCES.txt
runpy_tool.egg-info/dependency_links.txt
runpy_tool.egg-info/entry_points.txt
runpy_tool.egg-info/top_level.txt